fBrowser/__init__.py
fBrowser-0.3.1.dist-info/LICENSE.txt
fBrowser-0.3.1.dist-info/METADATA
fBrowser-0.3.1.dist-info/WHEEL
fBrowser-0.3.1.dist-info/top_level.txt
fBrowser-0.3.1.dist-info/RECORD
