Metadata-Version: 2.1
Name: fBrowser
Version: 0.3.1
Summary: Python3 library to make selenium webscraping easier
Home-page: https://github.com/FastestMolasses/fBrowser
Author: Abe
Author-email: 
License: UNKNOWN
Platform: UNKNOWN
Classifier: Programming Language :: Python :: 3
Classifier: License :: OSI Approved :: MIT License
Classifier: Operating System :: OS Independent
